{"type":3,"data":{"source":0,"texts":[],"attributes":[{"id":823,"attributes":{"style":{"transform":"translate3d(48.8823px, 0px, 0px)"}}},{"id":861,"attributes":{"style":{"transform":"translate(0%, 19.5529%) translate3d(0px, 0px, 0px)","opacity":"0.0224"}}},{"id":179,"attributes":{"style":{"transform":"translate3d(0px, 0px, 0px) scale(0.5111, 0.5111)","opacity":"0.0223"}}},{"id":174,"attributes":{"style":{"transform":"translate3d(0px, 0px, 0px) scale(0.5112, 0.5112)","opacity":"0.0223"}}},{"id":169,"attributes":{"style":{"transform":"translate3d(0px, 0px, 0px) scale(0.5112, 0.5112)","opacity":"0.0224"}}},{"id":164,"attributes":{"style":{"transform":"translate3d(0px, 0px, 0px) scale(0.5112, 0.5112)","opacity":"0.0224"}}},{"id":867,"attributes":{"style":{"transform":"translate3d(3.901px, 0px, 0px)"}}},{"id":905,"attributes":{"style":{"transform":"translate(0%, 3.901%) translate3d(0px, 0px, 0px)","opacity":"0.922"}}},{"id":187,"attributes":{"style":{"transform":"translate3d(0px, 0px, 0px) scale(0.961, 0.961)","opacity":"0.922"}}},{"id":192,"attributes":{"style":{"transform":"translate3d(0px, 0px, 0px) scale(0.9272, 0.9272)","opacity":"0.8544"}}},{"id":197,"attributes":{"style":{"transform":"translate3d(0px, 0px, 0px) scale(0.8642, 0.8642)","opacity":"0.7283"}}},{"id":202,"attributes":{"style":{"transform":"translate3d(0px, 0px, 0px) scale(0.7465, 0.7465)","opacity":"0.493"}}}],"removes":[],"adds":[]},"timestamp":1723387045318}