{"type":3,"data":{"source":0,"texts":[],"attributes":[{"id":902,"attributes":{"style":{"transform":"translate(-2.1576%, 0%) translate3d(0px, 0px, 0px)"}}},{"id":899,"attributes":{"style":{"transform":"translate(-2.1576%, 0%) translate3d(0px, 0px, 0px)"}}},{"id":896,"attributes":{"style":{"transform":"translate(-2.1576%, 0%) translate3d(0px, 0px, 0px)"}}},{"id":893,"attributes":{"style":{"transform":"translate(-2.1576%, 0%) translate3d(0px, 0px, 0px)"}}},{"id":890,"attributes":{"style":{"transform":"translate(-2.1576%, 0%) translate3d(0px, 0px, 0px)"}}},{"id":887,"attributes":{"style":{"transform":"translate(-2.1576%, 0%) translate3d(0px, 0px, 0px)"}}},{"id":883,"attributes":{"style":{"transform":"translate(-2.1576%, 0%) translate3d(0px, 0px, 0px)"}}},{"id":878,"attributes":{"style":{"transform":"translate(-2.1576%, 0%) translate3d(0px, 0px, 0px)"}}},{"id":875,"attributes":{"style":{"transform":"translate(-2.1576%, 0%) translate3d(0px, 0px, 0px)"}}},{"id":871,"attributes":{"style":{"transform":"translate(-2.1576%, 0%) translate3d(0px, 0px, 0px)"}}},{"id":905,"attributes":{"style":{"transform":"translate(0%, -1.2945%) translate3d(0px, 0px, 0px)","opacity":"0.9784"}}},{"id":202,"attributes":{"style":{"transform":"translate3d(-496.335px, -301.272px, 0px) scale(1.135, 1.1352)"}}},{"id":197,"attributes":{"style":{"transform":"translate3d(731.977px, -384.494px, 0px) scale(1.1359, 1.136)"}}},{"id":192,"attributes":{"style":{"transform":"translate3d(186.943px, 331.159px, 0px) scale(1.1364, 1.1365)"}}},{"id":187,"attributes":{"style":{"transform":"translate3d(813.154px, 167.182px, 0px) scale(1.1367, 1.1368)"}}}],"removes":[],"adds":[]},"timestamp":1723387046134}