{"type":3,"data":{"source":0,"texts":[],"attributes":[{"id":700,"attributes":{"style":{"transform":"translate3d(49.9122px, 0px, 0px)"}}},{"id":729,"attributes":{"style":{"transform":"translate(0%, 19.9824%) translate3d(0px, 0px, 0px)","opacity":"0.0018"}}},{"id":105,"attributes":{"style":{"transform":"translate3d(0px, 0px, 0px) scale(0.5002, 0.5002)","opacity":"0.0003"}}},{"id":100,"attributes":{"style":{"transform":"translate3d(0px, 0px, 0px) scale(0.5006, 0.5006)","opacity":"0.0012"}}},{"id":95,"attributes":{"style":{"transform":"translate3d(0px, 0px, 0px) scale(0.5009, 0.5009)","opacity":"0.0018"}}},{"id":735,"attributes":{"style":{"transform":"translate3d(1.566px, 0px, 0px)"}}},{"id":773,"attributes":{"style":{"transform":"translate(0%, 1.9505%) translate3d(0px, 0px, 0px)","opacity":"0.961"}}},{"id":118,"attributes":{"style":{"transform":"translate3d(0px, 0px, 0px) scale(0.9805, 0.9805)","opacity":"0.961"}}},{"id":123,"attributes":{"style":{"transform":"translate3d(0px, 0px, 0px) scale(0.9636, 0.9636)","opacity":"0.9272"}}},{"id":128,"attributes":{"style":{"transform":"translate3d(0px, 0px, 0px) scale(0.9321, 0.9321)","opacity":"0.8642"}}},{"id":133,"attributes":{"style":{"transform":"translate3d(0px, 0px, 0px) scale(0.8733, 0.8733)","opacity":"0.7465"}}}],"removes":[],"adds":[]},"timestamp":1723396463768}