{"type":3,"data":{"source":0,"texts":[],"attributes":[{"id":911,"attributes":{"style":{"transform":"translate3d(46.8978px, 0px, 0px)"}}},{"id":946,"attributes":{"style":{"transform":"translate(0%, 18.7728%) translate3d(0px, 0px, 0px)","opacity":"0.062"}}},{"id":225,"attributes":{"style":{"transform":"translate3d(0px, 0px, 0px) scale(0.5298, 0.5298)","opacity":"0.0595"}}},{"id":220,"attributes":{"style":{"transform":"translate3d(0px, 0px, 0px) scale(0.5305, 0.5305)","opacity":"0.0609"}}},{"id":215,"attributes":{"style":{"transform":"translate3d(0px, 0px, 0px) scale(0.5308, 0.5308)","opacity":"0.0616"}}},{"id":210,"attributes":{"style":{"transform":"translate3d(0px, 0px, 0px) scale(0.531, 0.531)","opacity":"0.062"}}},{"id":867,"attributes":{"style":{"transform":"translate3d(6.25px, 0px, 0px)"}}},{"id":905,"attributes":{"style":{"transform":"translate(0%, 6.25%) translate3d(0px, 0px, 0px)","opacity":"0.875"}}},{"id":187,"attributes":{"style":{"transform":"translate3d(0px, 0px, 0px) scale(0.9375, 0.9375)","opacity":"0.875"}}},{"id":192,"attributes":{"style":{"transform":"translate3d(0px, 0px, 0px) scale(0.8834, 0.8834)","opacity":"0.7667"}}},{"id":197,"attributes":{"style":{"transform":"translate3d(0px, 0px, 0px) scale(0.7824, 0.7824)","opacity":"0.5647"}}},{"id":202,"attributes":{"style":{"transform":"translate3d(0px, 0px, 0px) scale(0.5939, 0.5939)","opacity":"0.1877"}}}],"removes":[],"adds":[]},"timestamp":1723396468086}