{"type":3,"data":{"source":0,"texts":[],"attributes":[{"id":823,"attributes":{"style":{"transform":"translate3d(49.971px, 0px, 0px)"}}},{"id":861,"attributes":{"style":{"transform":"translate(0%, 20.0025%) translate3d(0px, 0px, 0px)","opacity":"0.0006"}}},{"id":169,"attributes":{"style":{"transform":"translate3d(0px, 0px, 0px) scale(0.5001, 0.5001)","opacity":"0.0002"}}},{"id":164,"attributes":{"style":{"transform":"translate3d(0px, 0px, 0px) scale(0.5003, 0.5003)","opacity":"0.0006"}}}],"removes":[],"adds":[]},"timestamp":1723396472486}