{"type":3,"data":{"source":0,"texts":[],"attributes":[{"id":700,"attributes":{"style":{"transform":"translate3d(50px, 0px, 0px)"}}},{"id":729,"attributes":{"style":{"transform":"translate(0%, 20%) translate3d(0px, 0px, 0px)"}}},{"id":735,"attributes":{"style":{"transform":"translate3d(0.7921px, 0px, 0px)"}}},{"id":773,"attributes":{"style":{"transform":"translate(0%, 0.7922%) translate3d(0px, 0px, 0px)","opacity":"0.9842"}}},{"id":118,"attributes":{"style":{"transform":"translate3d(0px, 0px, 0px) scale(0.9921, 0.9921)","opacity":"0.9842"}}},{"id":123,"attributes":{"style":{"transform":"translate3d(0px, 0px, 0px) scale(0.9852, 0.9852)","opacity":"0.9704"}}},{"id":128,"attributes":{"style":{"transform":"translate3d(0px, 0px, 0px) scale(0.9724, 0.9724)","opacity":"0.9448"}}},{"id":133,"attributes":{"style":{"transform":"translate3d(0px, 0px, 0px) scale(0.9485, 0.9485)","opacity":"0.8971"}}}],"removes":[],"adds":[]},"timestamp":1723396463217}