{"type":3,"data":{"source":0,"texts":[],"attributes":[{"id":700,"attributes":{"style":{"transform":"translate3d(49.9614px, 0px, 0px)"}}},{"id":729,"attributes":{"style":{"transform":"translate(0%, 19.9846%) translate3d(0px, 0px, 0px)","opacity":"0.0008"}}},{"id":110,"attributes":{"style":{"transform":"translate3d(0px, 0px, 0px) scale(0.5004, 0.5004)","opacity":"0.0008"}}},{"id":105,"attributes":{"style":{"transform":"translate3d(0px, 0px, 0px) scale(0.5004, 0.5004)","opacity":"0.0008"}}},{"id":100,"attributes":{"style":{"transform":"translate3d(0px, 0px, 0px) scale(0.5004, 0.5004)","opacity":"0.0008"}}},{"id":95,"attributes":{"style":{"transform":"translate3d(0px, 0px, 0px) scale(0.5004, 0.5004)","opacity":"0.0008"}}},{"id":659,"attributes":{"style":{"transform":"translate3d(49.7734px, 0px, 0px)"}}},{"id":694,"attributes":{"style":{"transform":"translate(0%, 20.1438%) translate3d(0px, 0px, 0px)","opacity":"0.0045"}}},{"id":72,"attributes":{"style":{"transform":"translate3d(0px, 0px, 0px) scale(0.5023, 0.5023)","opacity":"0.0045"}}}],"removes":[],"adds":[]},"timestamp":1723385786171}